tello_edu_py/__init__.py
tello_edu_py/comms_manager.py
tello_edu_py/fly_tello.py
tello_edu_py/tello.py
tello_edu_py-0.0.2.dist-info/LICENSE
tello_edu_py-0.0.2.dist-info/METADATA
tello_edu_py-0.0.2.dist-info/WHEEL
tello_edu_py-0.0.2.dist-info/top_level.txt
tello_edu_py-0.0.2.dist-info/RECORD
