Metadata-Version: 2.1
Name: tello-edu-py
Version: 0.0.2
Summary: Full-Featured Python SDK for Tello EDU
Home-page: https://github.com/tariq86/tello_edu.py
Author: Tariq86
Author-email: tariq.86@pm.me
License: UNKNOWN
Platform: UNKNOWN
Classifier: Programming Language :: Python :: 3
Classifier: License :: Public Domain
Classifier: Operating System :: OS Independent
Requires-Python: >=3.6
